{
  "citation": "Det. No. 17-0127, 36 WTD 601 (2017)",
  "date": "12/29/2017",
  "summary": "A former member of a closed LLC seeks a refund of money the member paid arising out of a trust fund assessment based on the closed LLC\u2019s unpaid retail sales taxes, asserting that he was not a responsible person for the closed LLC. The former member also contests the Department collecting money to satisfy the liability out of a bank account owned jointly by the former member and an unrelated third party. The former member is a former chief executive and is liable for the retail sales taxes assessed in the tax warrant against the closed LLC for the portion of the audit period where the former member was the chief executive. The petition is granted in part and denied in part.",
  "pdf_url": "https://dor.wa.gov/sites/default/files/2021-10/36_WTD601.pdf",
  "year": "2017",
  "filename": "36_WTD601.pdf",
  "downloaded_at": "2025-11-11 09:30:09"
}
