{
  "citation": "Det. No. 14-0310, 35 WTD 105 (2016)",
  "date": "03/31/2016",
  "summary": "Retail services provider argues that (i) the Department\u2019s assessment is barred by the statute of limitations; (ii) the installation of promotional displays inside retail stores is not a retail sale on the grounds that its customers are not \u201cconsumers\u201d; [(iii)] the performance of architectural site surveys is a professional service not subject to retail sales tax; and (iv) travel expense reimbursements are not subject to retail sales tax. The petition is denied.",
  "pdf_url": "https://dor.wa.gov/sites/default/files/2021-10/35WTD105.pdf",
  "year": "2016",
  "filename": "35WTD105.pdf",
  "downloaded_at": "2025-11-11 09:29:45"
}
