{
  "citation": "Det. No. 18-0231, 39 WTD 051 (2020)",
  "date": "04/30/2020",
  "summary": "A retailer of marijuana and marijuana-related products disputes the Department\u2019s estimated assessment of OTP tax on products referred to as cigar wraps or blunts. Taxpayer asserts that the products . . . do not contain tobacco. We find that the . . . cigar wraps contain tobacco and are subject to OTP tax. We deny Taxpayer\u2019s petition.",
  "pdf_url": "https://dor.wa.gov/sites/default/files/2021-10/39WTD051.pdf",
  "year": "2020",
  "filename": "39WTD051.pdf",
  "downloaded_at": "2025-11-11 09:42:41"
}