{
  "citation": "Det. No. 12-0104, 33 WTD 331 (2014)",
  "date": "07/31/2014",
  "summary": "Taxpayer, a yacht broker from California, is in the business of manufacturing and selling seagoing vessels. Taxpayer sold a yacht to a Washington resident and delivered the yacht to the buyer three miles off the coast of Port Townsend, Washington at or near coordinates N 48\u00b0 13\u2019 36\u201d W 122\u00b0 3\u2019 12\u201d. Taxpayer disputes the retail sales tax assessed against it by the Department of Revenue\u2019s Audit Division, claiming that it sold the yacht outside the borders of the State of Washington. We affirm the assessment and deny the Taxpayer\u2019s petition.",
  "pdf_url": "https://dor.wa.gov/sites/default/files/2021-10/33_WTD_331.pdf",
  "year": "2014",
  "filename": "33_WTD_331.pdf",
  "downloaded_at": "2025-11-11 09:24:49"
}