{
  "citation": "Det. No. 12-0157, 33 WTD 516 (2014)",
  "date": "10/31/2014",
  "summary": "A taxpayer in the business of fumigating shipping cargo containers and their contents for extermination and pest control purposes appeals an assessment reclassifying its gross income from the retailing B&O tax classification to the services and other activities tax classification. We affirm the assessment.",
  "pdf_url": "https://dor.wa.gov/sites/default/files/2021-10/33WTD516.pdf",
  "year": "2014",
  "filename": "33WTD516.pdf",
  "downloaded_at": "2025-11-11 09:24:15"
}