{
  "citation": "Det. No. 14-0095R, 34 WTD 155 (2015)",
  "date": "03/27/2015",
  "summary": "A taxpayer that collected and transported hazardous waste from Washington customers to its own hazardous waste disposal site [out-of-state] petitions for reconsideration. The taxpayer requests the Department rule that the costs of certain chemicals and binding reagents it uses to bind and dry hazardous waste before depositing that hazardous waste in its [out-of-state] landfill be allocated to [that state]. Taxpayer\u2019s petition for reconsideration is denied",
  "pdf_url": "https://dor.wa.gov/sites/default/files/2021-10/34WTD155.pdf",
  "year": "2015",
  "filename": "34WTD155.pdf",
  "downloaded_at": "2025-11-11 09:27:10"
}