{
  "citation": "Det. No. 20-0045, 41 WTD 126 (2022)",
  "date": "04/12/2022",
  "summary": "A broker-dealer that timely filed each of its required excise tax returns, but reported no business in every instance, protests the imposition of late payment and assessment penalties in connection with its annual reconciliation of apportionable income (ARAI) returns, arguing that the Department lacks the authority to impose such penalties in such cases. Petition denied.",
  "pdf_url": "https://dor.wa.gov/sites/default/files/2022-04/41WTD126.pdf",
  "year": "2022",
  "filename": "41WTD126.pdf",
  "downloaded_at": "2025-11-11 09:05:27"
}
